signalwire/__init__.py
signalwire/request_validator.py
signalwire/blade/__init__.py
signalwire/blade/connection.py
signalwire/blade/handler.py
signalwire/blade/helpers.py
signalwire/blade/messages/__init__.py
signalwire/blade/messages/connect.py
signalwire/blade/messages/execute.py
signalwire/blade/messages/message.py
signalwire/blade/messages/ping.py
signalwire/blade/messages/subscription.py
signalwire/fax_response/__init__.py
signalwire/messaging_response/__init__.py
signalwire/relay/__init__.py
signalwire/relay/client.py
signalwire/relay/constants.py
signalwire/relay/consumer.py
signalwire/relay/event.py
signalwire/relay/helpers.py
signalwire/relay/message_handler.py
signalwire/relay/task.py
signalwire/relay/calling/__init__.py
signalwire/relay/calling/call.py
signalwire/relay/calling/constants.py
signalwire/relay/calling/helpers.py
signalwire/relay/calling/actions/__init__.py
signalwire/relay/calling/actions/connect_action.py
signalwire/relay/calling/actions/detect_action.py
signalwire/relay/calling/actions/fax_action.py
signalwire/relay/calling/actions/play_action.py
signalwire/relay/calling/actions/prompt_action.py
signalwire/relay/calling/actions/record_action.py
signalwire/relay/calling/actions/send_digits_action.py
signalwire/relay/calling/actions/tap_action.py
signalwire/relay/calling/components/__init__.py
signalwire/relay/calling/components/answer.py
signalwire/relay/calling/components/awaiter.py
signalwire/relay/calling/components/base_fax.py
signalwire/relay/calling/components/connect.py
signalwire/relay/calling/components/decorators.py
signalwire/relay/calling/components/detect.py
signalwire/relay/calling/components/dial.py
signalwire/relay/calling/components/disconnect.py
signalwire/relay/calling/components/fax_receive.py
signalwire/relay/calling/components/fax_send.py
signalwire/relay/calling/components/hangup.py
signalwire/relay/calling/components/play.py
signalwire/relay/calling/components/prompt.py
signalwire/relay/calling/components/record.py
signalwire-2.1.0.dist-info/AUTHORS.md
signalwire-2.1.0.dist-info/LICENSE.md
signalwire-2.1.0.dist-info/METADATA
signalwire-2.1.0.dist-info/WHEEL
signalwire-2.1.0.dist-info/top_level.txt
signalwire-2.1.0.dist-info/RECORD
