Metadata-Version: 2.1
Name: signalwire
Version: 2.1.0
Summary: Client library for connecting to SignalWire.
Home-page: https://github.com/signalwire/signalwire-python
Author: SignalWire Team
Author-email: open.source@signalwire.com
License: MIT
Classifier: Development Status :: 5 - Production/Stable
Classifier: Intended Audience :: Developers
Classifier: Intended Audience :: Information Technology
Classifier: Intended Audience :: Telecommunications Industry
Classifier: License :: OSI Approved :: MIT License
Classifier: Natural Language :: English
Classifier: Topic :: Communications
Classifier: Topic :: Software Development
Requires-Python: >=3.6
License-File: LICENSE.md
License-File: AUTHORS.md
Requires-Dist: twilio ==6.54.0
Requires-Dist: aiohttp
